pyzeta/py.typed
pyzeta/core/__init__.py
pyzeta/core/distributions/__init__.py
pyzeta/core/distributions/abstract_ruelle.py
pyzeta/core/distributions/ruelle_distribution.py
pyzeta/core/dynamics/__init__.py
pyzeta/core/dynamics/function_systems/__init__.py
pyzeta/core/dynamics/function_systems/function_system.py
pyzeta/core/dynamics/function_systems/integral_provider.py
pyzeta/core/dynamics/function_systems/map_system.py
pyzeta/core/dynamics/function_systems/moebius_system.py
pyzeta/core/dynamics/function_systems/schottky_exception.py
pyzeta/core/dynamics/function_systems/schottky_system.py
pyzeta/core/dynamics/function_systems/symmetrized_integrals.py
pyzeta/core/dynamics/function_systems/helpers/__init__.py
pyzeta/core/dynamics/function_systems/helpers/schottky_helper.py
pyzeta/core/dynamics/function_systems/implementations/__init__.py
pyzeta/core/dynamics/function_systems/implementations/constant_integrals.py
pyzeta/core/dynamics/function_systems/implementations/fundomain_integrals.py
pyzeta/core/dynamics/function_systems/implementations/funnel_surface.py
pyzeta/core/dynamics/function_systems/implementations/funnel_torus.py
pyzeta/core/dynamics/function_systems/implementations/hyperbolic_cylinder.py
pyzeta/core/dynamics/function_systems/implementations/poincare_integrals.py
pyzeta/core/dynamics/symbolic_dynamics/__init__.py
pyzeta/core/dynamics/symbolic_dynamics/abstract_dynamics.py
pyzeta/core/dynamics/symbolic_dynamics/reduced_dynamics.py
pyzeta/core/dynamics/symbolic_dynamics/symbolic_dynamics.py
pyzeta/core/dynamics/symbolic_dynamics/helpers/__init__.py
pyzeta/core/dynamics/symbolic_dynamics/helpers/filters.py
pyzeta/core/factories/__init__.py
pyzeta/core/factories/function_systems.py
pyzeta/core/factories/integrals.py
pyzeta/core/factories/map_systems.py
pyzeta/core/factories/symbolics.py
pyzeta/core/factories/zetas.py
pyzeta/core/pyzeta_types/__init__.py
pyzeta/core/pyzeta_types/function_systems.py
pyzeta/core/pyzeta_types/general.py
PyZeta-0.1.0.dist-info/LICENSE
PyZeta-0.1.0.dist-info/METADATA
PyZeta-0.1.0.dist-info/WHEEL
PyZeta-0.1.0.dist-info/entry_points.txt
PyZeta-0.1.0.dist-info/top_level.txt
PyZeta-0.1.0.dist-info/RECORD
