Metadata-Version: 2.1
Name: PyZeta
Version: 0.1.0
Summary: Numerical project all about (dynamical) zeta functions and resonances.
Author-email: Philipp Schuette <pschuet2@mail.uni-paderborn.de>
License: GNU GENERAL PUBLIC LICENSE
Project-URL: homepage, https://github.com/Spectral-Analysis-UPB/PyZeta
Project-URL: documentation, https://pyzeta.readthedocs.io/en/latest/?badge=latest
Keywords: resonances,zeta functions,mathematical physics
Classifier: Programming Language :: Python :: 3
Classifier: License :: OSI Approved :: GNU General Public License v3 (GPLv3)
Classifier: Operating System :: OS Independent
Requires-Python: >=3.9
License-File: LICENSE
Requires-Dist: numpy >=1.24
Requires-Dist: cython
Requires-Dist: matplotlib
Requires-Dist: scipy >=1.9.1
Requires-Dist: typing-extensions
Requires-Dist: numba >=0.55.1
Requires-Dist: bokeh
Requires-Dist: pyzeal >=1.0.0
Provides-Extra: all
Requires-Dist: pyzeta[docs] ; extra == 'all'
Requires-Dist: pyzeta[dev] ; extra == 'all'
Provides-Extra: dev
Requires-Dist: mypy ; extra == 'dev'
Requires-Dist: mypy-extensions ; extra == 'dev'
Requires-Dist: hypothesis ; extra == 'dev'
Requires-Dist: pytest ; extra == 'dev'
Requires-Dist: pytest-cov ; extra == 'dev'
Requires-Dist: pytest-xdist ; extra == 'dev'
Requires-Dist: black ; extra == 'dev'
Requires-Dist: isort ; extra == 'dev'
Requires-Dist: docstr-coverage ; extra == 'dev'
Requires-Dist: pylama[toml] ; extra == 'dev'
Requires-Dist: pylint ; extra == 'dev'
Requires-Dist: check-jsonschema ; extra == 'dev'
Provides-Extra: docs
Requires-Dist: sphinx ; extra == 'docs'
Requires-Dist: sphinx-material ; extra == 'docs'
Requires-Dist: nbsphinx ; extra == 'docs'
Requires-Dist: sphinxcontrib-bibtex ; extra == 'docs'
Requires-Dist: sphinx-autodoc-typehints ; extra == 'docs'
Requires-Dist: sphinx-copybutton ; extra == 'docs'
